{"CURRICULO-VITAE":{"SISTEMA-ORIGEM-XML":"LATTES_OFFLINE","DATA-ATUALIZACAO":"27032012","HORA-ATUALIZACAO":"214452","NUMERO-IDENTIFICADOR":"","DADOS-GERAIS":{"NOME-COMPLETO":"Thiago Lima de Oliveira","NOME-EM-CITACOES-BIBLIOGRAFICAS":"OLIVEIRA, T. L.","NACIONALIDADE":"B","PAIS-DE-NASCIMENTO":"Brasil","UF-NASCIMENTO":"","CIDADE-NASCIMENTO":"","PERMISSAO-DE-DIVULGACAO":"NAO","DATA-FALECIMENTO":"","RESUMO-CV":{"TEXTO-RESUMO-CV-RH":"","TEXTO-RESUMO-CV-RH-EN":""},"OUTRAS-INFORMACOES-RELEVANTES":{"OUTRAS-INFORMACOES-RELEVANTES":""},"ENDERECO":{"FLAG-DE-PREFERENCIA":"ENDERECO_INSTITUCIONAL","ENDERECO-PROFISSIONAL":{"CODIGO-INSTITUICAO-EMPRESA":"","NOME-INSTITUICAO-EMPRESA":"","CODIGO-UNIDADE":"","NOME-UNIDADE":"","CODIGO-ORGAO":"","NOME-ORGAO":"","PAIS":"","UF":"","LOGRADOURO-COMPLEMENTO":"","BAIRRO":"","CIDADE":"","CAIXA-POSTAL":"","CEP":"","DDD":"","TELEFONE":"","RAMAL":"","FAX":"","HOME-PAGE":""}},"FORMACAO-ACADEMICA-TITULACAO":{"GRADUACAO":{"SEQUENCIA-FORMACAO":"2","NIVEL":"1","TITULO-DO-TRABALHO-DE-CONCLUSAO-DE-CURSO":"","NOME-DO-ORIENTADOR":"","CODIGO-INSTITUICAO":"869900000005","NOME-INSTITUICAO":"Instituto Militar de Engenharia","CODIGO-CURSO":"60171219","NOME-CURSO":"Engenharia da Computação","CODIGO-AREA-CURSO":"","STATUS-DO-CURSO":"EM_ANDAMENTO","ANO-DE-INICIO":"2010","ANO-DE-CONCLUSAO":"","FLAG-BOLSA":"NAO","CODIGO-AGENCIA-FINANCIADORA":"","NOME-AGENCIA":"","NUMERO-ID-ORIENTADOR":"","CODIGO-CURSO-CAPES":"50621","TITULO-DO-TRABALHO-DE-CONCLUSAO-DE-CURSO-INGLES":"","NOME-CURSO-INGLES":""},"ENSINO-MEDIO-SEGUNDO-GRAU":{"SEQUENCIA-FORMACAO":"1","NIVEL":"C","CODIGO-INSTITUICAO":"","NOME-INSTITUICAO":"Escola Preparatória de Cadetes do Ar","STATUS-DO-CURSO":"CONCLUIDO","ANO-DE-INICIO":"2004","ANO-DE-CONCLUSAO":"2006"}},"ATUACOES-PROFISSIONAIS":{"ATUACAO-PROFISSIONAL":{"CODIGO-INSTITUICAO":"0"}},"AREAS-DE-ATUACAO":{"AREA-DE-ATUACAO":{"SEQUENCIA-AREA-DE-ATUACAO":"1","NOME-GRANDE-AREA-DO-CONHECIMENTO":"OUTROS","NOME-DA-AREA-DO-CONHECIMENTO":"","NOME-DA-SUB-AREA-DO-CONHECIMENTO":"","NOME-DA-ESPECIALIDADE":""}},"IDIOMAS":{"IDIOMA":[{"IDIOMA":"ES","DESCRICAO-DO-IDIOMA":"Espanhol","PROFICIENCIA-DE-LEITURA":"RAZOAVELMENTE","PROFICIENCIA-DE-FALA":"POUCO","PROFICIENCIA-DE-ESCRITA":"POUCO","PROFICIENCIA-DE-COMPREENSAO":"POUCO"},{"IDIOMA":"EN","DESCRICAO-DO-IDIOMA":"Inglês","PROFICIENCIA-DE-LEITURA":"RAZOAVELMENTE","PROFICIENCIA-DE-FALA":"POUCO","PROFICIENCIA-DE-ESCRITA":"POUCO","PROFICIENCIA-DE-COMPREENSAO":"POUCO"}]},"PREMIOS-TITULOS":{"PREMIO-TITULO":[{"NOME-DO-PREMIO-OU-TITULO":"Reconhecimento da Seção de Engenharia Mecânica e de Materiais do IME por destacar-se com o trabalho \"Caracterização e Beneficiamento de Rejeito de Caulim para Síntese de Geopolímeros\"","NOME-DA-ENTIDADE-PROMOTORA":"Instituto Militar de Engenharia","ANO-DA-PREMIACAO":"2011","NOME-DO-PREMIO-OU-TITULO-INGLES":""},{"NOME-DO-PREMIO-OU-TITULO":"Medalha de bronze na Olimpíada Mineira de Matemática","NOME-DA-ENTIDADE-PROMOTORA":"Departamento de Matemática da Universidade Federal de Minas Gerais","ANO-DA-PREMIACAO":"2005","NOME-DO-PREMIO-OU-TITULO-INGLES":""}]}},"DADOS-COMPLEMENTARES":{"INFORMACOES-ADICIONAIS-INSTITUICOES":{"INFORMACAO-ADICIONAL-INSTITUICAO":{"CODIGO-INSTITUICAO":"869900000005","SIGLA-INSTITUICAO":"IME","SIGLA-UF-INSTITUICAO":"RJ","SIGLA-PAIS-INSTITUICAO":"BRA","NOME-PAIS-INSTITUICAO":"Brasil","FLAG-AGENCIA-FOMENTO":"NAO","FLAG-INSTITUICAO-DE-ENSINO":"SIM"}},"INFORMACOES-ADICIONAIS-CURSOS":{"INFORMACAO-ADICIONAL-CURSO":{"CODIGO-CURSO":"60171219","CODIGO-ORGAO":"","NOME-ORGAO":"","CODIGO-INSTITUICAO":"869900000005","NOME-INSTITUICAO":"Instituto Militar de Engenharia","NOME-GRANDE-AREA-DO-CONHECIMENTO":"OUTROS","NOME-DA-AREA-DO-CONHECIMENTO":"","NOME-DA-SUB-AREA-DO-CONHECIMENTO":"","NOME-DA-ESPECIALIDADE":"","NIVEL-CURSO":"GRADUACAO"}}}}}